cpp_compile_test/__init__.py
cpp_compile_test/__main__.py
cpp_compile_test/cli.py
cpp_compile_test/compile_source.py
cpp_compile_test/compile_test.py
cpp_compile_test/example_compile_test.hpp
cpp_compile_test/main.cpp
cpp_compile_test/test_discovery.py
cpp_compile_test/test_runner.py
cpp_compile_test/compiler_settings/__init__.py
cpp_compile_test/compiler_settings/compiler_settings.py
cpp_compile_test/compiler_settings/compiler_settings_schema.json
cpp_compile_test/compiler_settings/generate_from_schema.py
cpp_compile_test-1.0.0.dist-info/METADATA
cpp_compile_test-1.0.0.dist-info/WHEEL
cpp_compile_test-1.0.0.dist-info/entry_points.txt
cpp_compile_test-1.0.0.dist-info/licenses/LICENSE
cpp_compile_test-1.0.0.dist-info/RECORD
