Metadata-Version: 2.4
Name: cpp_compile_test
Version: 1.0.0
Summary: Compile-time test discovery and execution for C++ headers using Tree-sitter
Author-email: Austin Drury <drurya96@gmail.com>
License:                                  Apache License
License-File: LICENSE
Requires-Python: >=3.9
Requires-Dist: pydantic>=2.0
Requires-Dist: tree-sitter
